{"horoscope":{"Taureau":[{"jour":1,"phare":"La Paix Intérieure : Accordez-vous du temps pour la relaxation et la méditation.  L'harmonie est votre objectif principal aujourd'hui."},{"jour":2,"phare":"L'Énergie : Investissez dans votre bien-être physique. Une activité physique ou un soin vous revitaliseront."},{"jour":3,"phare":"L'Appréciation : Prenez le temps d'apprécier les petites choses de la vie.  La gratitude est une source de bonheur."},{"jour":4,"phare":"La Sécurité : Assurez-vous de votre confort et de votre sécurité.  La prévoyance est une qualité essentielle."},{"jour":5,"phare":"L'Investissement : Explorez de nouvelles opportunités financières.  Votre sens pratique vous guidera vers des choix judicieux."},{"jour":6,"phare":"La Tradition : Respectez vos racines et vos valeurs.  Le respect de l'héritage est important pour vous."},{"jour":7,"phare":"Le Plaisir : Offrez-vous un moment de détente et de plaisir.  Le bien-être est un droit."},{"jour":8,"phare":"La Connexion : Renforcez vos liens avec votre famille et vos amis.  Les relations sont essentielles."},{"jour":9,"phare":"L'Héritage :  Explorez vos passions.  Suivez vos instincts et vos intérêts personnels."},{"jour":10,"phare":"L'Art : Laissez libre cours à votre créativité.  L'expression artistique vous apportera joie et inspiration."},{"jour":11,"phare":"La Patience :  Soyez patient avec vous-même et avec les autres.  La persévérance est une vertu."},{"jour":12,"phare":"Le Confort : Créez un havre de paix chez vous.  Le bien-être physique est essentiel."},{"jour":13,"phare":"La Justice :  Agissez avec équité et honnêteté.  La vérité est toujours préférable."},{"jour":14,"phare":"La Collaboration : Travaillez en équipe et soyez ouvert aux idées des autres."},{"jour":15,"phare":"L'Amour :  Accordez de l'importance à vos relations amoureuses.  La tendresse est primordiale."},{"jour":16,"phare":"La Fertilité : Nourrissez votre potentiel créatif et productif."},{"jour":17,"phare":"La Nature : Passez du temps à l'extérieur et profitez des bienfaits de la nature."},{"jour":18,"phare":"Le Respect : Montrez de respect envers les personnes âgées et les traditions."},{"jour":19,"phare":"La Paix :  Recherchez la tranquillité d'esprit et la sérénité intérieure."},{"jour":20,"phare":"La Gratitude :  Exprimez votre gratitude pour les bonnes choses de votre vie."}],"Balance":[{"jour":1,"phare":"L'Équilibre : Priorisez vos besoins et vos limites.  L'harmonie est essentielle."},{"jour":2,"phare":"La Communication : Exprimez vos idées clairement.  Une conversation constructive peut résoudre des problèmes."},{"jour":3,"phare":"La Diplomatie :  Naviguez avec tact et diplomatie dans les situations difficiles."},{"jour":4,"phare":"La Collaboration : Travaillez en équipe et soyez ouvert aux idées des autres."},{"jour":5,"phare":"L'Esthétique : Accordez de l'importance à votre apparence.  Un environnement harmonieux vous inspirera."},{"jour":6,"phare":"La Justice :  Agissez avec équité et honnêteté.  La vérité est toujours préférable."},{"jour":7,"phare":"L'Art : Laissez libre cours à votre créativité.  L'expression artistique vous apportera joie et inspiration."},{"jour":8,"phare":"La Danse : Laissez-vous aller au rythme de la vie.  L'harmonie et le plaisir doivent être vos priorités."},{"jour":9,"phare":"Le Compromis : Soyez ouvert aux suggestions des autres.  La collaboration est la clé du succès."},{"jour":10,"phare":"L'Amour : Accordez de l'importance à vos relations amoureuses. La tendresse est primordiale."},{"jour":11,"phare":"La Paix : Recherchez la tranquillité d'esprit et la sérénité intérieure."},{"jour":12,"phare":"La Justice : Agissez avec équité et honnêteté. La vérité est toujours préférable."},{"jour":13,"phare":"Le Plaisir : Offrez-vous un moment de détente et de plaisir. Le bien-être est un droit."},{"jour":14,"phare":"La Gratitude : Exprimez votre gratitude pour les bonnes choses de votre vie."},{"jour":15,"phare":"La Nature : Passez du temps à l'extérieur et profitez des bienfaits de la nature."},{"jour":16,"phare":"La Créativité : Explorez vos idées et vos passions."},{"jour":17,"phare":"Le Travail : Trouvez un équilibre entre vos responsabilités et vos loisirs."},{"jour":18,"phare":"La Communication : Exprimez vos opinions avec respect et tact."},{"jour":19,"phare":"La Collaboration : Travaillez en équipe et soyez ouvert aux idées des autres."},{"jour":20,"phare":"La Liberté :  Profitez de vos libertés et de vos choix."}],"Lion":[{"jour":1,"phare":"L'Audace : Lancez-vous dans un nouveau projet.  Votre confiance en vous est votre plus grande force."},{"jour":2,"phare":"La Reconnaissance : Cultivez votre ego et vos talents.  Soyez fier de vos accomplissements."},{"jour":3,"phare":"L'Influence : Partagez votre leadership.  Votre capacité à inspirer les autres est votre atout."},{"jour":4,"phare":"La Performance : Concentrez-vous sur vos objectifs.  La discipline et la persévérance sont essentielles."},{"jour":5,"phare":"La Fête : Accordez-vous des moments de joie et de célébration.  Le plaisir est un besoin vital."},{"jour":6,"phare":"L'Art : Laissez libre cours à votre créativité.  L'expression artistique vous apportera joie et inspiration."},{"jour":7,"phare":"La Danse : Laissez-vous aller au rythme de la vie.  L'harmonie et le plaisir doivent être vos priorités."},{"jour":8,"phare":"La Reconnaissance :  Reconnaissez vos réussites et celles des autres."},{"jour":9,"phare":"L'Audace : Lancez-vous dans un nouveau projet. Votre confiance en vous est votre plus grande force."},{"jour":10,"phare":"La Performance : Concentrez-vous sur vos objectifs. La discipline et la persévérance sont essentielles."},{"jour":11,"phare":"La Fête : Accordez-vous des moments de joie et de célébration. Le plaisir est un besoin vital."},{"jour":12,"phare":"La Danse : Laissez-vous aller au rythme de la vie. L'harmonie et le plaisir doivent être vos priorités."},{"jour":13,"phare":"L'Influence : Partagez votre leadership. Votre capacité à inspirer les autres est votre atout."},{"jour":14,"phare":"La Reconnaissance :  Reconnaissez vos réussites et celles des autres."},{"jour":15,"phare":"L'Audace : Lancez-vous dans un nouveau projet. Votre confiance en vous est votre plus grande force."},{"jour":16,"phare":"L'Influence : Partagez votre leadership. Votre capacité à inspirer les autres est votre atout."},{"jour":17,"phare":"La Fête : Accordez-vous des moments de joie et de célébration. Le plaisir est un besoin vital."},{"jour":18,"phare":"La Performance : Concentrez-vous sur vos objectifs. La discipline et la persévérance sont essentielles."},{"jour":19,"phare":"La Reconnaissance : Reconnaissez vos réussites et celles des autres."},{"jour":20,"phare":"L'Audace : Lancez-vous dans un nouveau projet. Votre confiance en vous est votre plus grande force."}]}}